SINGLE_CYCLE/src/data_memory.v

module data_memory(input clk,
                   input  store_instruction,
                   input  [31:0]  address,
                   input  [31:0]  data_memory_in,
                   output [31:0]  data_memory_out);
    
    reg [31:0] data_mem [0:4096];

    initial begin
        data_mem[0] = 32'h00004430;
        data_mem[1] = 32'h00008610;
        data_mem[2] = 32'h00004430;
        data_mem[3] = 32'h00000193;
    end

    assign data_memory_out = data_mem[address[6:0]];

    always @(posedge clk) begin

    if(store_instruction)
        data_mem[address[6:0]] <= data_memory_in;

    if(store_instruction)
            $display("STORING  VALUE %h and mem[%h]", data_memory_in,address[6:0]);


    end


endmodule

MULTI_CYCLE_CACHE/src/core/branch_comparison.v


module branch_comparision (input wire [3:0]  branch_operation,
                           input wire [31:0] data_register_a,
                           input wire [31:0] data_register_b,
                           output reg branch);

    always @(*) begin
        case (branch_operation)
            4'b0001 : branch =  (data_register_a == data_register_b); //BEQ
            
            4'b0010 : branch =  (data_register_a > data_register_b);  //BGT

            4'b0011 : branch =  (data_register_a >= data_register_b); //BGE
            default: branch = 0;
        endcase
    end
    
    
endmodule

SINGLE_CYCLE/src/alu.v



module alu  (input wire [ 31 : 0 ] reg_a,
             input wire [ 31 : 0 ] reg_b,
             input wire [ 3 : 0 ] alu_ctrl,
             output reg [ 31 : 0 ] result_value );

    always @(*) begin
        case (alu_ctrl)
            4'b0001 : result_value = reg_a + reg_b; //ADD
            4'b0010 : result_value = reg_a - reg_b; //SUB
            4'b0011 : result_value = reg_a & reg_b; //AND
            4'b0100 : result_value = reg_a | reg_b; //OR
            default: result_value = 0;
        endcase
    end
    
endmodule

SINGLE_CYCLE/src/register_table.v

module register_table(input          clk,
                      input          reset,
                      input  [4:0]  register_a,
                      input  [4:0]  register_b,
                      input  [4:0]  register_d,
                      input  [31:0]  data_register_d_in,
                      input  write_register_d,
                      output  [31:0]  data_register_a,
                      output  [31:0]  data_register_b,
                      output  [31:0]  data_register_d_out
                      );
    

    reg [31:0] data_register [0:31];
    integer i;

    reg [31:0] rm0_pc_exception;
    reg [31:0] rm1_address_exception;

    reg [31:0] rm4_privilege_level;
    

    initial begin
        data_register[0] = 32'h00000001;
        data_register[1] = 32'h00000007;
        data_register[2] = 32'h00000004;
        data_register[3] = 32'h00000004;
    end

    assign data_register_a = data_register[register_a[4:0]];
    assign data_register_b = data_register[register_b[4:0]];
    assign data_register_d_out = data_register[register_d[4:0]];

    always @(posedge clk or reset) begin
    if(write_register_d)
        data_register[register_d[4:0]] <= data_register_d_in;
    else if (reset)
        for (i = 0; i < 32; i++) data_register[i] = 32'h0;
     end


endmodule

SINGLE_CYCLE/src/control.v

module control_module(  input [3:0] opcode ,
                        output wire alu_operation,
                        output reg [3:0] alu_operation_type,
                        output wire write_register,
                        output wire load_word_memory,
                        output wire store_word_memory,
                        output wire branch,
                        output reg [3:0] branch_operation_type,
                        output wire jump,
                        output reg panic);

     
    assign store_word_memory = (opcode == 4'b0010);

    assign branch_eq       = (opcode == 4'b0011);
    assign branch_gt       = (opcode == 4'b0100);
    assign branch_ge       = (opcode == 4'b0101);
    assign jump            = (opcode == 4'b0110);    

     

    assign alu_operation = (opcode == 4'b0000);
    assign load_word_memory  = (opcode == 4'b0001);
    assign write_register  = (opcode == 4'b0000) || (opcode == 4'b0001);

    always @(*) begin
        alu_operation_type = 4'b0000;
        branch_operation_type = 4'b0000;
        panic = ( opcode > 10);
        case(opcode)
            4'b0000: begin     //ADD
                alu_operation_type = 4'b0001;
                
                end
            // 4'b0000: begin     //SUB
            //     alu_operation_type = 4'b0010;
                
            //     end
            // 4'b0000: begin     //AND
            //     alu_operation_type = 4'b0011;
                
            //     end
            // 4'b0000: begin     //OR
            //     alu_operation_type = 4'b0100;
                
            //     end
            4'b0011: begin     //BE
                branch_operation_type = 4'b0001;
                
                end
            4'b0100: begin     //BGT
                branch_operation_type = 4'b0010;
                
                end
            4'b0101: begin     //BGE
                branch_operation_type = 4'b0011;
                
                end
        endcase
    end
    
endmodule

SINGLE_CYCLE/src/decode.v
module decode_instruction(
    input  wire [31:0] instruction,
    output wire [3:0]  opcode,
    output wire [4:0]  reg_a,
    output wire [4:0]  reg_b,
    output wire [4:0]  reg_d,
    output wire [12:0] offset
);


assign opcode = instruction[3:0];
assign reg_d  = instruction[8:4];
assign reg_b  = instruction[13:9];
assign reg_a  = instruction[18:14];

//Check the bits of the offset for the set of instructions
assign offset = instruction[31:19];

endmodule

SINGLE_CYCLE/src/instruction_memory.v

module instruction_memory(input  [31:0]  program_counter,
                          output  [31:0]  instruction_out);
    

    reg [31:0] instr_mem [0:255];


    initial begin
        instr_mem[0] = 32'h000044BB;
        //instr_mem[0] = 32'h00004416;
        instr_mem[1] = 32'h00000000;
        instr_mem[2] = 32'h00000000;
        instr_mem[3] = 32'h00004430;
        instr_mem[4] = 32'h00008610;
        instr_mem[5] = 32'h00000431;
        instr_mem[6] = 32'h00008610;
        instr_mem[7] = 32'h00000422;
        instr_mem[8] = 32'h00000431;
        instr_mem[9] = 32'h00000431;

    end

    assign instruction_out = instr_mem[program_counter[9:2]];


endmodule

// 0000000000000 00001 00010 00011 0000

// 0000000000000 00000 00110 01011 0001

// 0000000000000 00000 00010 00011 0001
// 0000000000000 00000 00010 00011 0001

 //0000000000011 00001 00001 00001 0011

// 00000000000000000000010000100010

SINGLE_CYCLE/src/fetch.v
module m_program_counter(
    input          clk,
    input  [12:0]  branch_target, // Address to jump to
    input          branch,        // Branch control
    input  [31:0]  jump_target,
    input          jump,           // Jump control
    input          reset,
    input          panic, 
    output [31:0]  pc_out         // Current PC
);

    // Registro para PC
    reg [31:0] PC_reg;
    
    initial begin
        PC_reg = 0;
    end



    always @(posedge clk or posedge reset) begin

        if(reset)
            PC_reg <= 0;
        else if (branch)
            PC_reg <= PC_reg + {19'b0, branch_target, 2'b00};
        else if (jump)
            PC_reg <=  {jump_target, 2'b00};
        else if (panic)
            PC_reg <=  32'hffffff0;
        else
            PC_reg <= PC_reg + 4;
    end

    assign pc_out = PC_reg;

endmodule

SINGLE_CYCLE/src/cpu.v


module cpu(input  wire clk,
           input  wire reset);


    wire [31:0] program_counter;
    wire [31:0] instruction;
    wire [3:0]  branch_type_operation;
    


    wire [31:0] data_register_a;
    wire [31:0] data_register_b;
    wire [31:0] data_register_d;
    wire [31:0] alu_output;

    reg [31:0] adress_data;
    


    wire [3:0] alu_type;
    
    wire [31:0] memory_data;
    wire reg_write, mem_write_word, mem_read_word, alu_operation_write_register, branch, jump, panic;
    wire [3:0]  opcode;
    wire [4:0]  reg_a;
    wire [4:0]  reg_b;
    wire [4:0]  reg_d;
    wire [12:0] offset;

    reg [31:0] new_register_data;


    m_program_counter pc(   .clk (clk),
                            .branch_target (offset),       // Dirección de PC desde fuera (por ejemplo, para saltos)
                            .branch (branch),
                            .jump_target(data_register_a),
                            .jump (jump),   
                            .reset (reset),
                            .panic (panic),           // Señal para elegir si actualizar PC normal o salto
                            .pc_out (program_counter)
                            );


    instruction_memory memory_ins( .program_counter (program_counter),
                                    .instruction_out (instruction) );

    decode_instruction decoder(   .instruction( instruction ),
                                    .opcode( opcode ),
                                    .reg_a( reg_a ),
                                    .reg_b( reg_b ),
                                    .reg_d( reg_d ),
                                    .offset( offset ));

    control_module control( .opcode( opcode ),
                            .alu_operation( alu_operation_write_register ),
                            .alu_operation_type(alu_type),
                            .write_register(reg_write),
                            .load_word_memory(mem_read_word),
                            .store_word_memory(mem_write_word),
                            .branch( branch ),
                            .branch_operation_type( branch_type_operation ),
                            .jump( jump ),
                            .panic( panic )); 

    register_table register_table( .clk(clk),
                        .register_a( reg_a ),
                        .register_b( reg_b ),
                        .register_d( reg_d ),
                        .data_register_d_in( new_register_data ),
                        .write_register_d( reg_write ),
                        .data_register_a( data_register_a ),
                        .data_register_b( data_register_b ),
                        .data_register_d_out ( data_register_d ));

    alu alu  ( .reg_a( data_register_a ),
               .reg_b( data_register_b ),
               .alu_ctrl( alu_type ),
               .result_value( alu_output ));

    branch_comparision branch_comp( .branch_operation (branch_type_operation),
                                    .data_register_a (data_register_a),
                                    .data_register_b (data_register_b),
                                    .branch (branch));


    always @(*) begin    //might change to clocked
        adress_data  = data_register_b;   
    end

    data_memory mem_data(.clk(clk),
                         .store_instruction (mem_write_word),
                         .address (adress_data),
                         .data_memory_in (data_register_d),
                         .data_memory_out (memory_data));


    always @(*) begin   //might change to clocked
        if (mem_read_word)
            new_register_data = memory_data;
        else if(alu_operation_write_register)
            new_register_data = alu_output;
        
    end






endmodule

SINGLE_CYCLE/tb/cpu_tb.v
`timescale 1ns/1ps

module tb_cpu;

    reg clk;
    reg reset;

    // Instantiate CPU
    cpu mycpu(
        .clk(clk),
        .reset(reset)
    );

    // Clock generation: 10 ns period
    initial clk = 0;
    always #5 clk = ~clk;

    // Test sequence
    initial begin
        $dumpfile("build/cpu_wave.vcd");
        $dumpvars(0, tb_cpu);
        $dumpvars(0, tb_cpu.mycpu.mem_data.data_mem[3]);
        reset = 0;
        // Reset CPU
        #0
        
        #10

        #20

        #40

        #70

        // Run simulation for a few cycles
        repeat (20) @(posedge clk);

        $finish;
    end

endmodule

SINGLE_CYCLE/build/cpu_wave.vcd
$date
	Sat Oct 25 18:10:22 2025
$end
$version
	Icarus Verilog
$end
$timescale
	1ps
$end
$scope module tb_cpu $end
$var reg 1 ! clk $end
$var reg 1 " reset $end
$scope module mycpu $end
$var wire 1 ! clk $end
$var wire 1 " reset $end
$var wire 1 # reg_write $end
$var wire 5 $ reg_d [4:0] $end
$var wire 5 % reg_b [4:0] $end
$var wire 5 & reg_a [4:0] $end
$var wire 32 ' program_counter [31:0] $end
$var wire 1 ( panic $end
$var wire 4 ) opcode [3:0] $end
$var wire 13 * offset [12:0] $end
$var wire 32 + memory_data [31:0] $end
$var wire 1 , mem_write_word $end
$var wire 1 - mem_read_word $end
$var wire 1 . jump $end
$var wire 32 / instruction [31:0] $end
$var wire 32 0 data_register_d [31:0] $end
$var wire 32 1 data_register_b [31:0] $end
$var wire 32 2 data_register_a [31:0] $end
$var wire 4 3 branch_type_operation [3:0] $end
$var wire 1 4 branch $end
$var wire 4 5 alu_type [3:0] $end
$var wire 32 6 alu_output [31:0] $end
$var wire 1 7 alu_operation_write_register $end
$var reg 32 8 adress_data [31:0] $end
$var reg 32 9 new_register_data [31:0] $end
$scope module alu $end
$var wire 32 : reg_b [31:0] $end
$var wire 32 ; reg_a [31:0] $end
$var wire 4 < alu_ctrl [3:0] $end
$var reg 32 = result_value [31:0] $end
$upscope $end
$scope module branch_comp $end
$var wire 32 > data_register_b [31:0] $end
$var wire 32 ? data_register_a [31:0] $end
$var wire 4 @ branch_operation [3:0] $end
$var reg 1 4 branch $end
$upscope $end
$scope module control $end
$var wire 1 4 branch $end
$var wire 1 # write_register $end
$var wire 1 , store_word_memory $end
$var wire 4 A opcode [3:0] $end
$var wire 1 - load_word_memory $end
$var wire 1 . jump $end
$var wire 1 B branch_gt $end
$var wire 1 C branch_ge $end
$var wire 1 D branch_eq $end
$var wire 1 7 alu_operation $end
$var reg 4 E alu_operation_type [3:0] $end
$var reg 4 F branch_operation_type [3:0] $end
$var reg 1 ( panic $end
$upscope $end
$scope module decoder $end
$var wire 5 G reg_d [4:0] $end
$var wire 5 H reg_b [4:0] $end
$var wire 5 I reg_a [4:0] $end
$var wire 4 J opcode [3:0] $end
$var wire 13 K offset [12:0] $end
$var wire 32 L instruction [31:0] $end
$upscope $end
$scope module mem_data $end
$var wire 32 M address [31:0] $end
$var wire 1 ! clk $end
$var wire 32 N data_memory_out [31:0] $end
$var wire 1 , store_instruction $end
$var wire 32 O data_memory_in [31:0] $end
$upscope $end
$scope module memory_ins $end
$var wire 32 P instruction_out [31:0] $end
$var wire 32 Q program_counter [31:0] $end
$upscope $end
$scope module pc $end
$var wire 1 4 branch $end
$var wire 13 R branch_target [12:0] $end
$var wire 1 ! clk $end
$var wire 1 . jump $end
$var wire 1 ( panic $end
$var wire 32 S pc_out [31:0] $end
$var wire 1 " reset $end
$var wire 32 T jump_target [31:0] $end
$var reg 32 U PC_reg [31:0] $end
$upscope $end
$scope module register_table $end
$var wire 1 ! clk $end
$var wire 32 V data_register_a [31:0] $end
$var wire 32 W data_register_b [31:0] $end
$var wire 32 X data_register_d_in [31:0] $end
$var wire 32 Y data_register_d_out [31:0] $end
$var wire 5 Z register_a [4:0] $end
$var wire 5 [ register_b [4:0] $end
$var wire 5 \ register_d [4:0] $end
$var wire 1 ] reset $end
$var wire 1 # write_register_d $end
$var integer 32 ^ i [31:0] $end
$upscope $end
$upscope $end
$upscope $end
$scope module tb_cpu $end
$scope module mycpu $end
$scope module mem_data $end
$var reg 32 _ \data_mem[3] [31:0] $end
$upscope $end
$upscope $end
$upscope $end
$enddefinitions $end
$comment Show the parameter values. $end
$dumpall
$end
#0
$dumpvars
b110010011 _
bx ^
z]
b1011 \
b10 [
b1 Z
bx Y
bx X
b100 W
b111 V
b0 U
b111 T
b0 S
b0 R
b0 Q
b100010010111011 P
bx O
bx N
b100 M
b100010010111011 L
b0 K
b1011 J
b1 I
b10 H
b1011 G
b0 F
b0 E
0D
0C
0B
b1011 A
b0 @
b111 ?
b100 >
b0 =
b0 <
b111 ;
b100 :
bx 9
b100 8
07
b0 6
b0 5
04
b0 3
b111 2
b100 1
bx 0
b100010010111011 /
0.
0-
0,
bx +
b0 *
b1011 )
1(
b0 '
b1 &
b10 %
b1011 $
0#
0"
0!
$end
#5000
bx 8
bx M
bx 2
bx ;
bx ?
bx T
bx V
bx 1
bx :
bx >
bx W
x#
x(
bx *
bx K
bx R
bx &
bx I
bx Z
bx %
bx H
bx [
bx $
bx G
bx \
x-
x7
x.
xC
xB
xD
x,
bx )
bx A
bx J
bx /
bx L
bx P
b1111111111111111111111110000 '
b1111111111111111111111110000 Q
b1111111111111111111111110000 S
b1111111111111111111111110000 U
1!
#10000
0!
#15000
b1111111111111111111111110100 '
b1111111111111111111111110100 Q
b1111111111111111111111110100 S
b1111111111111111111111110100 U
1!
#20000
0!
#25000
b1111111111111111111111111000 '
b1111111111111111111111111000 Q
b1111111111111111111111111000 S
b1111111111111111111111111000 U
1!
#30000
0!
#35000
b1111111111111111111111111100 '
b1111111111111111111111111100 Q
b1111111111111111111111111100 S
b1111111111111111111111111100 U
1!
#40000
0!
#45000
b100 8
b100 M
b111 2
b111 ;
b111 ?
b111 T
b111 V
b100 1
b100 :
b100 >
b100 W
0#
1(
b0 *
b0 K
b0 R
b1 &
b1 I
b1 Z
b10 %
b10 H
b10 [
b1011 $
b1011 G
b1011 \
0-
07
0.
0C
0B
0D
0,
b1011 )
b1011 A
b1011 J
b100010010111011 /
b100010010111011 L
b100010010111011 P
b10000000000000000000000000000 '
b10000000000000000000000000000 Q
b10000000000000000000000000000 S
b10000000000000000000000000000 U
1!
#50000
0!
#55000
bx 8
bx M
bx 2
bx ;
bx ?
bx T
bx V
bx 1
bx :
bx >
bx W
x#
x(
bx *
bx K
bx R
bx &
bx I
bx Z
bx %
bx H
bx [
bx $
bx G
bx \
x-
x7
x.
xC
xB
xD
x,
bx )
bx A
bx J
bx /
bx L
bx P
b1111111111111111111111110000 '
b1111111111111111111111110000 Q
b1111111111111111111111110000 S
b1111111111111111111111110000 U
1!
#60000
0!
#65000
b1111111111111111111111110100 '
b1111111111111111111111110100 Q
b1111111111111111111111110100 S
b1111111111111111111111110100 U
1!
#70000
0!
#75000
b1111111111111111111111111000 '
b1111111111111111111111111000 Q
b1111111111111111111111111000 S
b1111111111111111111111111000 U
1!
#80000
0!
#85000
b1111111111111111111111111100 '
b1111111111111111111111111100 Q
b1111111111111111111111111100 S
b1111111111111111111111111100 U
1!
#90000
0!
#95000
b100 8
b100 M
b111 2
b111 ;
b111 ?
b111 T
b111 V
b100 1
b100 :
b100 >
b100 W
0#
1(
b0 *
b0 K
b0 R
b1 &
b1 I
b1 Z
b10 %
b10 H
b10 [
b1011 $
b1011 G
b1011 \
0-
07
0.
0C
0B
0D
0,
b1011 )
b1011 A
b1011 J
b100010010111011 /
b100010010111011 L
b100010010111011 P
b10000000000000000000000000000 '
b10000000000000000000000000000 Q
b10000000000000000000000000000 S
b10000000000000000000000000000 U
1!
#100000
0!
#105000
bx 8
bx M
bx 2
bx ;
bx ?
bx T
bx V
bx 1
bx :
bx >
bx W
x#
x(
bx *
bx K
bx R
bx &
bx I
bx Z
bx %
bx H
bx [
bx $
bx G
bx \
x-
x7
x.
xC
xB
xD
x,
bx )
bx A
bx J
bx /
bx L
bx P
b1111111111111111111111110000 '
b1111111111111111111111110000 Q
b1111111111111111111111110000 S
b1111111111111111111111110000 U
1!
#110000
0!
#115000
b1111111111111111111111110100 '
b1111111111111111111111110100 Q
b1111111111111111111111110100 S
b1111111111111111111111110100 U
1!
#120000
0!
#125000
b1111111111111111111111111000 '
b1111111111111111111111111000 Q
b1111111111111111111111111000 S
b1111111111111111111111111000 U
1!
#130000
0!
#135000
b1111111111111111111111111100 '
b1111111111111111111111111100 Q
b1111111111111111111111111100 S
b1111111111111111111111111100 U
1!
#140000
0!
#145000
b100 8
b100 M
b111 2
b111 ;
b111 ?
b111 T
b111 V
b100 1
b100 :
b100 >
b100 W
0#
1(
b0 *
b0 K
b0 R
b1 &
b1 I
b1 Z
b10 %
b10 H
b10 [
b1011 $
b1011 G
b1011 \
0-
07
0.
0C
0B
0D
0,
b1011 )
b1011 A
b1011 J
b100010010111011 /
b100010010111011 L
b100010010111011 P
b10000000000000000000000000000 '
b10000000000000000000000000000 Q
b10000000000000000000000000000 S
b10000000000000000000000000000 U
1!
#150000
0!
#155000
bx 8
bx M
bx 2
bx ;
bx ?
bx T
bx V
bx 1
bx :
bx >
bx W
x#
x(
bx *
bx K
bx R
bx &
bx I
bx Z
bx %
bx H
bx [
bx $
bx G
bx \
x-
x7
x.
xC
xB
xD
x,
bx )
bx A
bx J
bx /
bx L
bx P
b1111111111111111111111110000 '
b1111111111111111111111110000 Q
b1111111111111111111111110000 S
b1111111111111111111111110000 U
1!
#160000
0!
#165000
b1111111111111111111111110100 '
b1111111111111111111111110100 Q
b1111111111111111111111110100 S
b1111111111111111111111110100 U
1!
#170000
0!
#175000
b1111111111111111111111111000 '
b1111111111111111111111111000 Q
b1111111111111111111111111000 S
b1111111111111111111111111000 U
1!
#180000
0!
#185000
b1111111111111111111111111100 '
b1111111111111111111111111100 Q
b1111111111111111111111111100 S
b1111111111111111111111111100 U
1!
#190000
0!
#195000
b100 8
b100 M
b111 2
b111 ;
b111 ?
b111 T
b111 V
b100 1
b100 :
b100 >
b100 W
0#
1(
b0 *
b0 K
b0 R
b1 &
b1 I
b1 Z
b10 %
b10 H
b10 [
b1011 $
b1011 G
b1011 \
0-
07
0.
0C
0B
0D
0,
b1011 )
b1011 A
b1011 J
b100010010111011 /
b100010010111011 L
b100010010111011 P
b10000000000000000000000000000 '
b10000000000000000000000000000 Q
b10000000000000000000000000000 S
b10000000000000000000000000000 U
1!
#200000
0!
#205000
bx 8
bx M
bx 2
bx ;
bx ?
bx T
bx V
bx 1
bx :
bx >
bx W
x#
x(
bx *
bx K
bx R
bx &
bx I
bx Z
bx %
bx H
bx [
bx $
bx G
bx \
x-
x7
x.
xC
xB
xD
x,
bx )
bx A
bx J
bx /
bx L
bx P
b1111111111111111111111110000 '
b1111111111111111111111110000 Q
b1111111111111111111111110000 S
b1111111111111111111111110000 U
1!
#210000
0!
#215000
b1111111111111111111111110100 '
b1111111111111111111111110100 Q
b1111111111111111111111110100 S
b1111111111111111111111110100 U
1!
#220000
0!
#225000
b1111111111111111111111111000 '
b1111111111111111111111111000 Q
b1111111111111111111111111000 S
b1111111111111111111111111000 U
1!
#230000
0!
#235000
b1111111111111111111111111100 '
b1111111111111111111111111100 Q
b1111111111111111111111111100 S
b1111111111111111111111111100 U
1!
#240000
0!
#245000
b100 8
b100 M
b111 2
b111 ;
b111 ?
b111 T
b111 V
b100 1
b100 :
b100 >
b100 W
0#
1(
b0 *
b0 K
b0 R
b1 &
b1 I
b1 Z
b10 %
b10 H
b10 [
b1011 $
b1011 G
b1011 \
0-
07
0.
0C
0B
0D
0,
b1011 )
b1011 A
b1011 J
b100010010111011 /
b100010010111011 L
b100010010111011 P
b10000000000000000000000000000 '
b10000000000000000000000000000 Q
b10000000000000000000000000000 S
b10000000000000000000000000000 U
1!
#250000
0!
#255000
bx 8
bx M
bx 2
bx ;
bx ?
bx T
bx V
bx 1
bx :
bx >
bx W
x#
x(
bx *
bx K
bx R
bx &
bx I
bx Z
bx %
bx H
bx [
bx $
bx G
bx \
x-
x7
x.
xC
xB
xD
x,
bx )
bx A
bx J
bx /
bx L
bx P
b1111111111111111111111110000 '
b1111111111111111111111110000 Q
b1111111111111111111111110000 S
b1111111111111111111111110000 U
1!
#260000
0!
#265000
b1111111111111111111111110100 '
b1111111111111111111111110100 Q
b1111111111111111111111110100 S
b1111111111111111111111110100 U
1!
#270000
0!
#275000
b1111111111111111111111111000 '
b1111111111111111111111111000 Q
b1111111111111111111111111000 S
b1111111111111111111111111000 U
1!
#280000
0!
#285000
b1111111111111111111111111100 '
b1111111111111111111111111100 Q
b1111111111111111111111111100 S
b1111111111111111111111111100 U
1!
#290000
0!
#295000
b100 8
b100 M
b111 2
b111 ;
b111 ?
b111 T
b111 V
b100 1
b100 :
b100 >
b100 W
0#
1(
b0 *
b0 K
b0 R
b1 &
b1 I
b1 Z
b10 %
b10 H
b10 [
b1011 $
b1011 G
b1011 \
0-
07
0.
0C
0B
0D
0,
b1011 )
b1011 A
b1011 J
b100010010111011 /
b100010010111011 L
b100010010111011 P
b10000000000000000000000000000 '
b10000000000000000000000000000 Q
b10000000000000000000000000000 S
b10000000000000000000000000000 U
1!
#300000
0!
#305000
bx 8
bx M
bx 2
bx ;
bx ?
bx T
bx V
bx 1
bx :
bx >
bx W
x#
x(
bx *
bx K
bx R
bx &
bx I
bx Z
bx %
bx H
bx [
bx $
bx G
bx \
x-
x7
x.
xC
xB
xD
x,
bx )
bx A
bx J
bx /
bx L
bx P
b1111111111111111111111110000 '
b1111111111111111111111110000 Q
b1111111111111111111111110000 S
b1111111111111111111111110000 U
1!
#310000
0!
#315000
b1111111111111111111111110100 '
b1111111111111111111111110100 Q
b1111111111111111111111110100 S
b1111111111111111111111110100 U
1!
#320000
0!
#325000
b1111111111111111111111111000 '
b1111111111111111111111111000 Q
b1111111111111111111111111000 S
b1111111111111111111111111000 U
1!
#330000
0!
#335000
b1111111111111111111111111100 '
b1111111111111111111111111100 Q
b1111111111111111111111111100 S
b1111111111111111111111111100 U
1!
