SINGLE_CYCLE/src/data_memory.v

module data_memory(input clk,
                   input  store_instruction,
                   input  [31:0]  address,
                   input  [31:0]  data_memory_in,
                   output [31:0]  data_memory_out);
    
    reg [31:0] data_mem [0:4096];

    initial begin
        data_mem[0] = 32'h00004430;
        data_mem[1] = 32'h00008610;
        data_mem[2] = 32'h00004430;
        data_mem[3] = 32'h00000193;
    end

    assign data_memory_out = data_mem[address[6:0]];

    always @(posedge clk) begin

    if(store_instruction)
        data_mem[address[6:0]] <= data_memory_in;

    if(store_instruction)
            $display("STORING  VALUE %h and mem[%h]", data_memory_in,address[6:0]);


    end


endmodule

SINGLE_CYCLE/src/alu.v



module alu  (input wire [ 31 : 0 ] reg_a,
             input wire [ 31 : 0 ] reg_b,
             input wire [ 3 : 0 ] alu_ctrl,
             output reg [ 31 : 0 ] result_value );

    always @(*) begin
        case (alu_ctrl)
            4'b0001 : result_value = reg_a + reg_b; //ADD
            4'b0010 : result_value = reg_a - reg_b; //SUB
            4'b0011 : result_value = reg_a & reg_b; //AND
            4'b0100 : result_value = reg_a | reg_b; //OR
            4'b0101 : result_value = reg_a * reg_b; //MULT

            default: result_value = 0;
        endcase
    end
    
endmodule

SINGLE_CYCLE/src/register_table.v

module register_table(input          clk,
                      input          reset,
                      input  [4:0]  register_a,
                      input  [4:0]  register_b,
                      input  [4:0]  register_d,
                      input  [31:0]  data_register_d_in,
                      input  write_register_d,
                      output  [31:0]  data_register_a,
                      output  [31:0]  data_register_b,
                      output  [31:0]  data_register_d_out
                      );
    

    reg [31:0] data_register [0:31];
    integer i;

    reg [31:0] rm0_pc_exception;
    reg [31:0] rm1_address_exception;

    reg [31:0] rm4_privilege_level;
    

    initial begin
        data_register[0] = 32'h00000001;
        data_register[1] = 32'h00000002;
        data_register[2] = 32'h00000003;
        data_register[3] = 32'h00000004;
    end

    assign data_register_a = data_register[register_a[4:0]];
    assign data_register_b = data_register[register_b[4:0]];
    assign data_register_d_out = data_register[register_d[4:0]];

    always @(posedge clk or reset) begin
    if(write_register_d)
        data_register[register_d[4:0]] <= data_register_d_in;
    else if (reset)
        for (i = 0; i < 32; i++) data_register[i] = 32'h0;
     end


endmodule

SINGLE_CYCLE/src/control.v

module control_module(  input [3:0] opcode ,
                        output wire alu_operation,
                        output reg [3:0] alu_operation_type,
                        output wire write_register,
                        output wire load_word_memory,
                        output wire store_word_memory,
                        output wire branch);

     
    assign store_word_memory = (opcode == 4'b0010);
    assign branch       = (opcode == 4'b0011);

    assign alu_operation = (opcode == 4'b0000);
    assign load_word_memory  = (opcode == 4'b0001);
    assign write_register  = (opcode == 4'b0000) || (opcode == 4'b0001);

    always @(*) begin
        alu_operation_type = 4'b0000;
        case(opcode)
            4'b0000: begin     //ADD
                alu_operation_type = 4'b0001;
                
                end
            4'b0000: begin     //SUB
                alu_operation_type = 4'b0010;
                
                end
            4'b0000: begin     //AND
                alu_operation_type = 4'b0011;
                
                end
            4'b0000: begin     //OR
                alu_operation_type = 4'b0100;
                
                end
        endcase
    end
    
endmodule

SINGLE_CYCLE/src/decode.v
module decode_instruction(
    input  wire [31:0] instruction,
    output wire [3:0]  opcode,
    output wire [4:0]  reg_a,
    output wire [4:0]  reg_b,
    output wire [4:0]  reg_d,
    output wire [12:0] offset
);


assign opcode = instruction[3:0];
assign reg_d  = instruction[8:4];
assign reg_b  = instruction[13:9];
assign reg_a  = instruction[18:14];

//Check the bits of the offset for the set of instructions
assign offset = instruction[31:19];

endmodule

SINGLE_CYCLE/src/instruction_memory.v

module instruction_memory(input  [31:0]  program_counter,
                          output  [31:0]  instruction_out);
    

    reg [31:0] instr_mem [0:255];


    initial begin
        instr_mem[0] = 32'h00004430;
        instr_mem[1] = 32'h00008610;
        instr_mem[2] = 32'h00000431;
        instr_mem[3] = 32'h00008610;
        instr_mem[4] = 32'h00000422;
        instr_mem[5] = 32'h00000431;
        instr_mem[6] = 32'h00000431;

    end

    assign instruction_out = instr_mem[program_counter[9:2]];


endmodule

// 0000000000000 00001 00010 00011 0000

// 0000000000000 00000 00110 01011 0001

// 0000000000000 00000 00010 00011 0001
// 0000000000000 00000 00010 00011 0001

// 00000000000000000000010000100010

SINGLE_CYCLE/src/fetch.v
module m_program_counter(
    input          clk,
    input  [31:0]  branch_target, // Address to jump to
    input          branch,        // Branch control
    input          reset,
    output [31:0]  pc_out         // Current PC
);

    // Registro para PC
    reg [31:0] PC_reg;



    always @(posedge clk or posedge reset) begin

        if(reset)
            PC_reg <= 0;
        else 
            PC_reg <= PC_reg + 4;
    end

    assign pc_out = PC_reg;

endmodule

SINGLE_CYCLE/src/cpu.v


module cpu(input  wire clk,
           input  wire reset);


    wire [31:0] program_counter;
    wire [31:0] instruction;
    wire [31:0] instruction_branch;
    wire [31:0] branch_target;


    wire [31:0] data_register_a;
    wire [31:0] data_register_b;
    wire [31:0] data_register_d;
    wire [31:0] alu_output;

    reg [31:0] adress_data;


    wire [3:0] alu_type;
    
    wire [31:0] memory_data;
    wire reg_write, mem_write_word, mem_read_word, alu_operation_write_register, branch;
    wire [3:0]  opcode;
    wire [4:0]  reg_a;
    wire [4:0]  reg_b;
    wire [4:0]  reg_d;
    wire [12:0] offset;

    reg [31:0] new_register_data;


    m_program_counter pc(   .clk (clk),
                            .branch_target (branch_target),       // Dirección de PC desde fuera (por ejemplo, para saltos)
                            .branch (branch),    
                            .reset (reset),           // Señal para elegir si actualizar PC normal o salto
                            .pc_out (program_counter)
                            );


    instruction_memory memory_ins( .program_counter (program_counter),
                                    .instruction_out (instruction) );

    decode_instruction decoder(   .instruction( instruction ),
                                    .opcode( opcode ),
                                    .reg_a( reg_a ),
                                    .reg_b( reg_b ),
                                    .reg_d( reg_d ),
                                    .offset( offset ));

    control_module control( .opcode( opcode ),
                            .alu_operation( alu_operation_write_register ),
                            .alu_operation_type(alu_type),
                            .write_register(reg_write),
                            .load_word_memory(mem_read_word),
                            .store_word_memory(mem_write_word),
                            .branch( branch )); 

    register_table register_table( .clk(clk),
                        .register_a( reg_a ),
                        .register_b( reg_b ),
                        .register_d( reg_d ),
                        .data_register_d_in( new_register_data ),
                        .write_register_d( reg_write ),
                        .data_register_a( data_register_a ),
                        .data_register_b( data_register_b ),
                        .data_register_d_out ( data_register_d ));

    alu alu  ( .reg_a( data_register_a ),
               .reg_b( data_register_b ),
               .alu_ctrl( alu_type ),
               .result_value( alu_output ));


    always @(*) begin    //might change to clocked
        adress_data  = data_register_b;   
    end

    data_memory mem_data(.clk(clk),
                         .store_instruction (mem_write_word),
                         .address (adress_data),
                         .data_memory_in (data_register_d),
                         .data_memory_out (memory_data));


    always @(*) begin   //might change to clocked
        if (mem_read_word)
            new_register_data = memory_data;
        else if(alu_operation_write_register)
            new_register_data = alu_output;
        
    end






endmodule

SINGLE_CYCLE/tb/cpu_tb.v
`timescale 1ns/1ps

module tb_cpu;

    reg clk;
    reg reset;

    // Instantiate CPU
    cpu mycpu(
        .clk(clk),
        .reset(reset)
    );

    // Clock generation: 10 ns period
    initial clk = 0;
    always #5 clk = ~clk;

    // Test sequence
    initial begin
        $dumpfile("build/cpu_wave.vcd");
        $dumpvars(0, tb_cpu);
        $dumpvars(0, tb_cpu.mycpu.mem_data.data_mem[3]);

        // Reset CPU
        reset = 1;
        #5 
        reset = 0;
        #10

        #20

        #40

        #70

        // Run simulation for a few cycles
        repeat (20) @(posedge clk);

        $finish;
    end

endmodule

SINGLE_CYCLE/build/cpu_wave.vcd
$date
	Sat Oct 25 15:54:07 2025
$end
$version
	Icarus Verilog
$end
$timescale
	1ps
$end
$scope module tb_cpu $end
$var reg 1 ! clk $end
$var reg 1 " reset $end
$scope module mycpu $end
$var wire 32 # branch_target [31:0] $end
$var wire 1 ! clk $end
$var wire 1 " reset $end
$var wire 1 $ reg_write $end
$var wire 5 % reg_d [4:0] $end
$var wire 5 & reg_b [4:0] $end
$var wire 5 ' reg_a [4:0] $end
$var wire 32 ( program_counter [31:0] $end
$var wire 4 ) opcode [3:0] $end
$var wire 13 * offset [12:0] $end
$var wire 32 + memory_data [31:0] $end
$var wire 1 , mem_write_word $end
$var wire 1 - mem_read_word $end
$var wire 32 . instruction [31:0] $end
$var wire 32 / data_register_d [31:0] $end
$var wire 32 0 data_register_b [31:0] $end
$var wire 32 1 data_register_a [31:0] $end
$var wire 1 2 branch $end
$var wire 4 3 alu_type [3:0] $end
$var wire 32 4 alu_output [31:0] $end
$var wire 1 5 alu_operation_write_register $end
$var reg 32 6 adress_data [31:0] $end
$var reg 32 7 new_register_data [31:0] $end
$scope module alu $end
$var wire 32 8 reg_b [31:0] $end
$var wire 32 9 reg_a [31:0] $end
$var wire 4 : alu_ctrl [3:0] $end
$var reg 32 ; result_value [31:0] $end
$upscope $end
$scope module control $end
$var wire 1 $ write_register $end
$var wire 1 , store_word_memory $end
$var wire 4 < opcode [3:0] $end
$var wire 1 - load_word_memory $end
$var wire 1 2 branch $end
$var wire 1 5 alu_operation $end
$var reg 4 = alu_operation_type [3:0] $end
$upscope $end
$scope module decoder $end
$var wire 5 > reg_d [4:0] $end
$var wire 5 ? reg_b [4:0] $end
$var wire 5 @ reg_a [4:0] $end
$var wire 4 A opcode [3:0] $end
$var wire 13 B offset [12:0] $end
$var wire 32 C instruction [31:0] $end
$upscope $end
$scope module mem_data $end
$var wire 32 D address [31:0] $end
$var wire 1 ! clk $end
$var wire 32 E data_memory_out [31:0] $end
$var wire 1 , store_instruction $end
$var wire 32 F data_memory_in [31:0] $end
$upscope $end
$scope module memory_ins $end
$var wire 32 G instruction_out [31:0] $end
$var wire 32 H program_counter [31:0] $end
$upscope $end
$scope module pc $end
$var wire 1 2 branch $end
$var wire 32 I branch_target [31:0] $end
$var wire 1 ! clk $end
$var wire 32 J pc_out [31:0] $end
$var wire 1 " reset $end
$var reg 32 K PC_reg [31:0] $end
$upscope $end
$scope module register_table $end
$var wire 1 ! clk $end
$var wire 32 L data_register_a [31:0] $end
$var wire 32 M data_register_b [31:0] $end
$var wire 32 N data_register_d_in [31:0] $end
$var wire 32 O data_register_d_out [31:0] $end
$var wire 5 P register_a [4:0] $end
$var wire 5 Q register_b [4:0] $end
$var wire 5 R register_d [4:0] $end
$var wire 1 S reset $end
$var wire 1 $ write_register_d $end
$var integer 32 T i [31:0] $end
$upscope $end
$upscope $end
$upscope $end
$scope module tb_cpu $end
$scope module mycpu $end
$scope module mem_data $end
$var reg 32 U \data_mem[3] [31:0] $end
$upscope $end
$upscope $end
$upscope $end
$enddefinitions $end
$comment Show the parameter values. $end
$dumpall
$end
#0
$dumpvars
b110010011 U
bx T
zS
b11 R
b10 Q
b1 P
b100 O
b101 N
b11 M
b10 L
b0 K
b0 J
bz I
b0 H
b100010000110000 G
b100 F
b110010011 E
b11 D
b100010000110000 C
b0 B
b0 A
b1 @
b10 ?
b11 >
b1 =
b0 <
b101 ;
b1 :
b10 9
b11 8
b101 7
b11 6
15
b101 4
b1 3
02
b10 1
b11 0
b100 /
b100010000110000 .
0-
0,
b110010011 +
b0 *
b0 )
b0 (
b1 '
b10 &
b11 %
1$
bz #
1"
0!
$end
#5000
bx +
bx E
b1000 7
b1000 N
b101 6
b101 D
b1000 4
b1000 ;
b11 1
b11 9
b11 L
b101 0
b101 8
b101 M
b10 '
b10 @
b10 P
b11 &
b11 ?
b11 Q
b1 %
b1 >
b1 R
b1000011000010000 .
b1000011000010000 C
b1000011000010000 G
b100 (
b100 H
b100 J
b100 K
b10 /
b10 F
b10 O
0"
1!
#10000
0!
#15000
b110010011 +
b110010011 E
b11 6
b11 D
b0 4
b0 ;
b1 1
b1 9
b1 L
b11 0
b11 8
b11 M
b110010011 7
b110010011 N
b0 3
b0 :
b0 =
b0 '
b0 @
b0 P
b10 &
b10 ?
b10 Q
b11 %
b11 >
b11 R
1-
05
b1 )
b1 <
b1 A
b10000110001 .
b10000110001 C
b10000110001 G
b1000 (
b1000 H
b1000 J
b1000 K
b101 /
b101 F
b101 O
1!
#20000
0!
#25000
bx +
bx E
b110010011 6
b110010011 D
b110010110 4
b110010110 ;
b11 1
b11 9
b11 L
b110010011 0
b110010011 8
b110010011 M
b110010110 7
b110010110 N
b1 3
b1 :
b1 =
b10 '
b10 @
b10 P
b11 &
b11 ?
b11 Q
b1 %
b1 >
b1 R
0-
15
b0 )
b0 <
b0 A
b1000011000010000 .
b1000011000010000 C
b1000011000010000 G
b1100 (
b1100 H
b1100 J
b1100 K
b1000 /
b1000 F
b1000 O
1!
#30000
0!
#35000
b110010011 +
b110010011 E
b11 6
b11 D
b0 4
b0 ;
b1 1
b1 9
b1 L
b11 0
b11 8
b11 M
0$
b0 3
b0 :
b0 =
b0 '
b0 @
b0 P
b10 &
b10 ?
b10 Q
b10 %
b10 >
b10 R
05
1,
b10 )
b10 <
b10 A
b10000100010 .
b10000100010 C
b10000100010 G
b10000 (
b10000 H
b10000 J
b10000 K
b11 /
b11 F
b11 O
1!
#40000
0!
#45000
b110010011 /
b110010011 F
b110010011 O
1$
b11 7
b11 N
b11 %
b11 >
b11 R
1-
0,
b1 )
b1 <
b1 A
b10000110001 .
b10000110001 C
b10000110001 G
b11 U
b11 +
b11 E
b10100 (
b10100 H
b10100 J
b10100 K
1!
#50000
0!
#55000
b11000 (
b11000 H
b11000 J
b11000 K
b11 /
b11 F
b11 O
1!
#60000
0!
#65000
bx +
bx E
bx 6
bx D
bx 1
bx 9
bx L
bx 0
bx 8
bx M
bx /
bx F
bx O
x$
bx *
bx B
bx '
bx @
bx P
bx &
bx ?
bx Q
bx %
bx >
bx R
x-
x5
x2
x,
bx )
bx <
bx A
bx .
bx C
bx G
b11100 (
b11100 H
b11100 J
b11100 K
1!
#70000
0!
#75000
b100000 (
b100000 H
b100000 J
b100000 K
1!
#80000
0!
#85000
b100100 (
b100100 H
b100100 J
b100100 K
1!
#90000
0!
#95000
b101000 (
b101000 H
b101000 J
b101000 K
1!
#100000
0!
#105000
b101100 (
b101100 H
b101100 J
b101100 K
1!
#110000
0!
#115000
b110000 (
b110000 H
b110000 J
b110000 K
1!
#120000
0!
#125000
b110100 (
b110100 H
b110100 J
b110100 K
1!
#130000
0!
#135000
b111000 (
b111000 H
b111000 J
b111000 K
1!
#140000
0!
#145000
b111100 (
b111100 H
b111100 J
b111100 K
1!
#150000
0!
#155000
b1000000 (
b1000000 H
b1000000 J
b1000000 K
1!
#160000
0!
#165000
b1000100 (
b1000100 H
b1000100 J
b1000100 K
1!
#170000
0!
#175000
b1001000 (
b1001000 H
b1001000 J
b1001000 K
1!
#180000
0!
#185000
b1001100 (
b1001100 H
b1001100 J
b1001100 K
1!
#190000
0!
#195000
b1010000 (
b1010000 H
b1010000 J
b1010000 K
1!
#200000
0!
#205000
b1010100 (
b1010100 H
b1010100 J
b1010100 K
1!
#210000
0!
#215000
b1011000 (
b1011000 H
b1011000 J
b1011000 K
1!
#220000
0!
#225000
b1011100 (
b1011100 H
b1011100 J
b1011100 K
1!
#230000
0!
#235000
b1100000 (
b1100000 H
b1100000 J
b1100000 K
1!
#240000
0!
#245000
b1100100 (
b1100100 H
b1100100 J
b1100100 K
1!
#250000
0!
#255000
b1101000 (
b1101000 H
b1101000 J
b1101000 K
1!
#260000
0!
#265000
b1101100 (
b1101100 H
b1101100 J
b1101100 K
1!
#270000
0!
#275000
b1110000 (
b1110000 H
b1110000 J
b1110000 K
1!
#280000
0!
#285000
b1110100 (
b1110100 H
b1110100 J
b1110100 K
1!
#290000
0!
#295000
b1111000 (
b1111000 H
b1111000 J
b1111000 K
1!
#300000
0!
#305000
b1111100 (
b1111100 H
b1111100 J
b1111100 K
1!
#310000
0!
#315000
b10000000 (
b10000000 H
b10000000 J
b10000000 K
1!
#320000
0!
#325000
b10000100 (
b10000100 H
b10000100 J
b10000100 K
1!
#330000
0!
#335000
b10001000 (
b10001000 H
b10001000 J
b10001000 K
1!
